CHANGELOG
LICENSE.txt
MANIFEST.in
README.md
setup.py
cx_pyqtgraph/PlotData.py
cx_pyqtgraph/Point.py
cx_pyqtgraph/Qt.py
cx_pyqtgraph/SRTTransform.py
cx_pyqtgraph/SRTTransform3D.py
cx_pyqtgraph/SignalProxy.py
cx_pyqtgraph/ThreadsafeTimer.py
cx_pyqtgraph/Transform3D.py
cx_pyqtgraph/Vector.py
cx_pyqtgraph/WidgetGroup.py
cx_pyqtgraph/__init__.py
cx_pyqtgraph/colormap.py
cx_pyqtgraph/configfile.py
cx_pyqtgraph/debug.py
cx_pyqtgraph/exceptionHandling.py
cx_pyqtgraph/frozenSupport.py
cx_pyqtgraph/functions.py
cx_pyqtgraph/graphicsWindows.py
cx_pyqtgraph/numpy_fix.py
cx_pyqtgraph/ordereddict.py
cx_pyqtgraph/pgcollections.py
cx_pyqtgraph/ptime.py
cx_pyqtgraph/python2_3.py
cx_pyqtgraph/reload.py
cx_pyqtgraph/units.py
cx_pyqtgraph.egg-info/PKG-INFO
cx_pyqtgraph.egg-info/SOURCES.txt
cx_pyqtgraph.egg-info/dependency_links.txt
cx_pyqtgraph.egg-info/requires.txt
cx_pyqtgraph.egg-info/top_level.txt
cx_pyqtgraph/GraphicsScene/GraphicsScene.py
cx_pyqtgraph/GraphicsScene/__init__.py
cx_pyqtgraph/GraphicsScene/exportDialog.py
cx_pyqtgraph/GraphicsScene/exportDialogTemplate_pyqt.py
cx_pyqtgraph/GraphicsScene/exportDialogTemplate_pyqt5.py
cx_pyqtgraph/GraphicsScene/exportDialogTemplate_pyside.py
cx_pyqtgraph/GraphicsScene/exportDialogTemplate_pyside2.py
cx_pyqtgraph/GraphicsScene/mouseEvents.py
cx_pyqtgraph/canvas/Canvas.py
cx_pyqtgraph/canvas/CanvasItem.py
cx_pyqtgraph/canvas/CanvasManager.py
cx_pyqtgraph/canvas/CanvasTemplate_pyqt.py
cx_pyqtgraph/canvas/CanvasTemplate_pyqt5.py
cx_pyqtgraph/canvas/CanvasTemplate_pyside.py
cx_pyqtgraph/canvas/CanvasTemplate_pyside2.py
cx_pyqtgraph/canvas/TransformGuiTemplate_pyqt.py
cx_pyqtgraph/canvas/TransformGuiTemplate_pyqt5.py
cx_pyqtgraph/canvas/TransformGuiTemplate_pyside.py
cx_pyqtgraph/canvas/TransformGuiTemplate_pyside2.py
cx_pyqtgraph/canvas/__init__.py
cx_pyqtgraph/console/CmdInput.py
cx_pyqtgraph/console/Console.py
cx_pyqtgraph/console/__init__.py
cx_pyqtgraph/console/template_pyqt.py
cx_pyqtgraph/console/template_pyqt5.py
cx_pyqtgraph/console/template_pyside.py
cx_pyqtgraph/console/template_pyside2.py
cx_pyqtgraph/dockarea/Container.py
cx_pyqtgraph/dockarea/Dock.py
cx_pyqtgraph/dockarea/DockArea.py
